tei_iiif/__init__.py
tei_iiif/__main__.py
tei_iiif/divjson.py
tei_iiif/getfile.py
tei_iiif/manifestgen.py
tei_iiif/settings.yaml
tei_iiif/tempfilegen.py
tei_iiif/xmlparser.py
tei_iiif/utils/__init__.py
tei_iiif/utils/cleanup.py
tei_iiif/utils/settings.py
TEI_IIIF-0.9.2.dist-info/LICENSE
TEI_IIIF-0.9.2.dist-info/METADATA
TEI_IIIF-0.9.2.dist-info/WHEEL
TEI_IIIF-0.9.2.dist-info/top_level.txt
TEI_IIIF-0.9.2.dist-info/RECORD
