Metadata-Version: 2.1
Name: TEI-IIIF
Version: 0.9.2
Summary: A Python CLI app that pulls data from TEI-XML files and transforms them to conformant IIIF Annotation manifests.
Author-email: Joshua Phillips <joshua.phillips@ell.ox.ac.uk>
Project-URL: Homepage, https://github.com/joshuaAPhillips/tei-iiif
Project-URL: Bug Tracker, https://github.com/joshuaAPhillips/tei-iiif/issues
Classifier: Programming Language :: Python :: 3
Classifier: License :: OSI Approved :: Apache Software License
Classifier: Operating System :: OS Independent
Requires-Python: >=3.7
License-File: LICENSE
Requires-Dist: lxml
Requires-Dist: natsort
Requires-Dist: pyyaml
Requires-Dist: requests
